aes256gcm_nacl-0.1.6-py2.7-nspkg.pth
aes256gcm_nacl-0.1.6.dist-info/DESCRIPTION.rst
aes256gcm_nacl-0.1.6.dist-info/METADATA
aes256gcm_nacl-0.1.6.dist-info/RECORD
aes256gcm_nacl-0.1.6.dist-info/WHEEL
aes256gcm_nacl-0.1.6.dist-info/metadata.json
aes256gcm_nacl-0.1.6.dist-info/namespace_packages.txt
aes256gcm_nacl-0.1.6.dist-info/top_level.txt
zerodbext/_aes256gcm_sodium.so
zerodbext/aead/__init__.py
zerodbext/aead/encoding.py
zerodbext/aead/exceptions.py
zerodbext/aead/utils.py
zerodbext/aead/bindings/__init__.py
zerodbext/aead/bindings/crypto_aead_aes256gcm.py
zerodbext/aead/bindings/sodium_core.py
