Metadata-Version: 2.0
Name: aes256gcm-nacl
Version: 0.1.6
Summary: aes256gcm support based on pynacl
Home-page: UNKNOWN
Author: XueYu
Author-email: 278006819@qq.com
License: AGPLv3
Platform: UNKNOWN
Classifier: Programming Language :: Python :: Implementation :: CPython
Classifier: Programming Language :: Python :: Implementation :: PyPy
Classifier: Programming Language :: Python :: 2
Classifier: Programming Language :: Python :: 2.6
Classifier: Programming Language :: Python :: 2.7
Classifier: Programming Language :: Python :: 3
Classifier: Programming Language :: Python :: 3.3
Classifier: Programming Language :: Python :: 3.4
Classifier: Programming Language :: Python :: 3.5
Requires-Dist: cffi (>=1.1.0)
Requires-Dist: six
Provides-Extra: tests
Requires-Dist: pytest; extra == 'tests'
